Anas_Ahmed_Project/Main.py
Anas_Ahmed_Project/Test.py
Anas_Ahmed_Project/__init__.py
Anas_Ahmed_Project-0.1.0.dist-info/METADATA
Anas_Ahmed_Project-0.1.0.dist-info/WHEEL
Anas_Ahmed_Project-0.1.0.dist-info/top_level.txt
Anas_Ahmed_Project-0.1.0.dist-info/RECORD
